oldaplib/__init__.py
oldaplib/ontologies/admin-testing.trig
oldaplib/ontologies/admin.trig
oldaplib/ontologies/example.trig
oldaplib/ontologies/oldap.trig
oldaplib/ontologies/oldap.ttl
oldaplib/ontologies/shared.trig
oldaplib/ontologies/standard/.gitsave
oldaplib/src/__init__.py
oldaplib/src/cachesingleton.py
oldaplib/src/connection.py
oldaplib/src/datamodel.py
oldaplib/src/dtypes/__init__.py
oldaplib/src/dtypes/bnode.py
oldaplib/src/dtypes/languagein.py
oldaplib/src/dtypes/namespaceiri.py
oldaplib/src/dtypes/rdfset.py
oldaplib/src/dtypes/xsdset.py
oldaplib/src/enums/__init__.py
oldaplib/src/enums/action.py
oldaplib/src/enums/adminpermissions.py
oldaplib/src/enums/attributeclass.py
oldaplib/src/enums/datapermissions.py
oldaplib/src/enums/externalontologyattr.py
oldaplib/src/enums/haspropertyattr.py
oldaplib/src/enums/language.py
oldaplib/src/enums/oldaplistattr.py
oldaplib/src/enums/oldaplistnodeattr.py
oldaplib/src/enums/owlpropertytype.py
oldaplib/src/enums/permissionsetattr.py
oldaplib/src/enums/projectattr.py
oldaplib/src/enums/propertyclassattr.py
oldaplib/src/enums/resourceclassattr.py
oldaplib/src/enums/sparql_result_format.py
oldaplib/src/enums/userattr.py
oldaplib/src/enums/xsd_datatypes.py
oldaplib/src/externalontology.py
oldaplib/src/globalconfig.py
oldaplib/src/hasproperty.py
oldaplib/src/helpers/Notify.py
oldaplib/src/helpers/__init__.py
oldaplib/src/helpers/attributechange.py
oldaplib/src/helpers/context.py
oldaplib/src/helpers/convert2datatype.py
oldaplib/src/helpers/irincname.py
oldaplib/src/helpers/json_encoder.py
oldaplib/src/helpers/langstring.py
oldaplib/src/helpers/numeric.py
oldaplib/src/helpers/observable_dict.py
oldaplib/src/helpers/observable_set.py
oldaplib/src/helpers/oldaperror.py
oldaplib/src/helpers/query_processor.py
oldaplib/src/helpers/semantic_version.py
oldaplib/src/helpers/serializeableset.py
oldaplib/src/helpers/serializer.py
oldaplib/src/helpers/singletonmeta.py
oldaplib/src/helpers/tools.py
oldaplib/src/iconnection.py
oldaplib-0.3.30.dist-info/METADATA
oldaplib-0.3.30.dist-info/WHEEL
oldaplib-0.3.30.dist-info/RECORD
