Metadata-Version: 2.1
Name: oldaplib
Version: 0.3.30
Summary: Open Media Access Server Library (Linked Open Data middleware/RESTApi)
License: GNU Affero General Public License version 3
Author: Lukas Rosenthaler
Author-email: lukas.rosenthaler@unibas.ch
Requires-Python: >=3.12,<4.0
Classifier: License :: Other/Proprietary License
Classifier: Programming Language :: Python :: 3
Classifier: Programming Language :: Python :: 3.12
Requires-Dist: bcrypt (==5.0.0)
Requires-Dist: bump2version (>=1.0.1,<2.0.0)
Requires-Dist: cloudpickle (>=3.1.1,<4.0.0)
Requires-Dist: coverage (>=7.10.7,<8.0.0)
Requires-Dist: isodate (>=0.7.2,<0.8.0)
Requires-Dist: lazydocs (>=0.4.8,<0.5.0)
Requires-Dist: mkdocs (>=1.5.3,<2.0.0)
Requires-Dist: mkdocs-material (==9.6.21)
Requires-Dist: mkdocstrings (>=0.30.0,<0.31.0)
Requires-Dist: mkdocstrings-python (>=1.17.0,<2.0.0)
Requires-Dist: pyjwt (>=2.8.0,<3.0.0)
Requires-Dist: pymdown-extensions (>=10.10.2,<11.0.0)
Requires-Dist: pyshacl (>=0.30.1,<0.31.0)
Requires-Dist: pystrict (>=1.3,<2.0)
Requires-Dist: pyyaml (>=6.0.2,<7.0.0)
Requires-Dist: rdflib (>=7.0.0,<8.0.0)
Requires-Dist: redis (>=6.4.0,<7.0.0)
Requires-Dist: requests (>=2.32.5,<3.0.0)
Requires-Dist: setuptools (>=80.9.0,<81.0.0)
Requires-Dist: validators (>=0.35.0,<0.36.0)
Requires-Dist: xmlschema (>=4.1.0,<5.0.0)
Requires-Dist: yamale (>=6.0.0,<7.0.0)
